spr/__init__.py
spr/cli.py
spr/config.py
spr/engine.py
spr/wsgi.py
spotify_podcast_rss-0.3.3.dist-info/LICENSE
spotify_podcast_rss-0.3.3.dist-info/METADATA
spotify_podcast_rss-0.3.3.dist-info/WHEEL
spotify_podcast_rss-0.3.3.dist-info/entry_points.txt
spotify_podcast_rss-0.3.3.dist-info/top_level.txt
spotify_podcast_rss-0.3.3.dist-info/RECORD
