Metadata-Version: 2.1
Name: spotify-podcast-rss
Version: 0.3.3
Summary: RSS for Spotify podcasts
Home-page: https://github.com/Eboreg/spotify-podcast-rss
Author: Robert Huselius
Author-email: robert@huseli.us
License: UNKNOWN
Platform: UNKNOWN
Classifier: Programming Language :: Python :: 3
Classifier: License :: OSI Approved :: GNU General Public License v3 (GPLv3)
Classifier: Operating System :: OS Independent
Classifier: Development Status :: 4 - Beta
Classifier: Environment :: Console
Classifier: Intended Audience :: Developers
Classifier: Topic :: Internet :: WWW/HTTP :: Dynamic Content
Classifier: Topic :: Internet :: WWW/HTTP :: Indexing/Search
Classifier: Topic :: Software Development :: Libraries :: Python Modules
Classifier: Topic :: Multimedia :: Sound/Audio
Requires-Python: >=3.5
Requires-Dist: feedgen
Requires-Dist: python-dateutil
Requires-Dist: spotipy
